blockrand_q_designer.py
blockrand_q_designer-0.1.0.dist-info/LICENSE
blockrand_q_designer-0.1.0.dist-info/METADATA
blockrand_q_designer-0.1.0.dist-info/WHEEL
blockrand_q_designer-0.1.0.dist-info/top_level.txt
blockrand_q_designer-0.1.0.dist-info/RECORD
