Metadata-Version: 2.2
Name: blockrand_q_designer
Version: 0.1.0
Summary: A tool for generating block randomized LC-MS queue designs for full factorial experiments.
Home-page: https://github.com/nar-g/blockrand_q_designer
Author: Guido Narduzzi
Author-email: narduzzi.guido@gmail.com
Classifier: Programming Language :: Python :: 3
Classifier: License :: OSI Approved :: MIT License
Classifier: Operating System :: OS Independent
Requires-Python: >=3.6
License-File: LICENSE
Requires-Dist: numpy
Dynamic: author
Dynamic: author-email
Dynamic: classifier
Dynamic: description
Dynamic: description-content-type
Dynamic: home-page
Dynamic: requires-dist
Dynamic: requires-python
Dynamic: summary
